lubit/__init__.py
lubit/client.py
lubit/exceptions.py
lubit/helpers.py
lubit-0.1.0.dist-info/METADATA
lubit-0.1.0.dist-info/WHEEL
lubit-0.1.0.dist-info/licenses/LICENSE
lubit-0.1.0.dist-info/RECORD
