Metadata-Version: 2.4
Name: lubit
Version: 0.1.0
Summary: Official Python client for the Lubit Energy Prediction Market API
Project-URL: Homepage, https://lubit.com
Project-URL: Documentation, https://lubit.com/api-docs
Project-URL: Repository, https://github.com/lubit-com/python-lubit
Project-URL: Issues, https://github.com/lubit-com/python-lubit/issues
Author-email: Lubit <api@lubit.com>
License: MIT
License-File: LICENSE
Keywords: api,electricity,energy,lubit,market,prediction,trading
Classifier: Development Status :: 4 - Beta
Classifier: Intended Audience :: Developers
Classifier: License :: OSI Approved :: MIT License
Classifier: Operating System :: OS Independent
Classifier: Programming Language :: Python :: 3
Classifier: Programming Language :: Python :: 3.7
Classifier: Programming Language :: Python :: 3.8
Classifier: Programming Language :: Python :: 3.9
Classifier: Programming Language :: Python :: 3.10
Classifier: Programming Language :: Python :: 3.11
Classifier: Programming Language :: Python :: 3.12
Classifier: Topic :: Software Development :: Libraries :: Python Modules
Requires-Python: >=3.7
Requires-Dist: requests>=2.25.0
